dumcure/__init__.py
dumcure/dumcure.py
dumcure-0.2.1.dist-info/entry_points.txt
dumcure-0.2.1.dist-info/METADATA
dumcure-0.2.1.dist-info/WHEEL
dumcure-0.2.1.dist-info/RECORD
