Metadata-Version: 2.1
Name: dumcure
Version: 0.2.1
Summary: Simple package which displays current currencies.
Author: buzonek
Author-email: buzonekk@gmail.com
Requires-Python: >=3.11,<4.0
Classifier: Programming Language :: Python :: 3
Classifier: Programming Language :: Python :: 3.11
Requires-Dist: requests (>=2.28.1,<3.0.0)
